py_skipgram_24/__init__.py
py_skipgram_24/preprocessor.py
py_skipgram_24/py_skipgram_24.py
py_skipgram_24/utils.py
py_skipgram_24-0.2.0.dist-info/LICENSE
py_skipgram_24-0.2.0.dist-info/METADATA
py_skipgram_24-0.2.0.dist-info/WHEEL
py_skipgram_24-0.2.0.dist-info/RECORD
